CHANGES.rst
MANIFEST.in
README.rst
requirements.txt
setup.cfg
setup.py
odoo_report_testing/__init__.py
odoo_report_testing/assertions.py
odoo_report_testing/reports.py
odoo_report_testing.egg-info/PKG-INFO
odoo_report_testing.egg-info/SOURCES.txt
odoo_report_testing.egg-info/dependency_links.txt
odoo_report_testing.egg-info/top_level.txt