Metadata-Version: 1.1
Name: odoo-report-testing
Version: 0.1
Summary: UNKNOWN
Home-page: https://github.com/anybox/selenium-configurator
Author: Odoo Community Association (OCA)
Author-email: support@odoo-community.org
License: AGPLV3
Platform: UNKNOWN
Classifier: Development Status :: 4 - Beta
Classifier: Environment :: Console
Classifier: Intended Audience :: Developers
Classifier: Intended Audience :: Information Technology
Classifier: License :: OSI Approved :: GNU Affero General Public License v3 or later (AGPLv3+)
Classifier: Topic :: Software Development :: Quality Assurance
Classifier: Topic :: Software Development :: Testing
Classifier: Topic :: Utilities
Classifier: Programming Language :: Python
Classifier: Programming Language :: Python :: 2.7
Classifier: Operating System :: POSIX :: Linux
